consite/__init__.py
consite/cli.py
consite/conserve.py
consite/hmmer_local.py
consite/msa_io.py
consite/parse_domtbl.py
consite/pfam.py
consite/structure.py
consite/utils.py
consite/viz.py
consite-0.1.6.dist-info/licenses/LICENSE
consite-0.1.6.dist-info/METADATA
consite-0.1.6.dist-info/WHEEL
consite-0.1.6.dist-info/entry_points.txt
consite-0.1.6.dist-info/top_level.txt
consite-0.1.6.dist-info/RECORD
