Metadata-Version: 2.4
Name: consite
Version: 0.1.6
Summary: ConSite: conserved-domain alignment and conserved-site visualization from protein FASTA
Author: Joey Wagner, Yang Li
License: MIT License
Project-URL: Homepage, https://github.com/yangli-evo/ConSite
Project-URL: Repository, https://github.com/yangli-evo/ConSite
Classifier: Programming Language :: Python :: 3
Classifier: Programming Language :: Python :: 3 :: Only
Classifier: License :: OSI Approved :: MIT License
Classifier: Operating System :: OS Independent
Classifier: Topic :: Scientific/Engineering :: Bio-Informatics
Requires-Python: >=3.10
License-File: LICENSE
Requires-Dist: biopython>=1.81
Requires-Dist: pandas>=2.0
Requires-Dist: numpy>=2.0
Requires-Dist: scipy<2.0,>=1.11
Requires-Dist: matplotlib>=3.7
Requires-Dist: pyMSAviz>=0.5.0
Dynamic: license-file
